LICENSE
README.md
pyproject.toml
setup.py
src/certify4py/Issuer.py
src/certify4py/UniversityDiplomaIssuer.py
src/certify4py/__init__.py
src/certify4py/certify_sc_utils.py
src/certify4py/chainpoint.py
src/certify4py/json_utils.py
src/certify4py/pdf.py
src/certify4py/university_abi.py
src/certify4py/utils.py
src/certify4py.egg-info/PKG-INFO
src/certify4py.egg-info/SOURCES.txt
src/certify4py.egg-info/dependency_links.txt
src/certify4py.egg-info/requires.txt
src/certify4py.egg-info/top_level.txt