Metadata-Version: 2.1
Name: certify4py
Version: 0.1.6
Summary: Issue certificates using blockchain and smart contract
Home-page: https://github.com/teo-mn/certify4py
Author: Surenbayar Doloonjin
Author-email: surenbayar@teo.mn
License: UNKNOWN
Project-URL: Bug Tracker, https://github.com/teo-mn/certify4py/issues
Platform: UNKNOWN
Classifier: Programming Language :: Python :: 3
Classifier: License :: OSI Approved :: MIT License
Classifier: Operating System :: OS Independent
Requires-Python: >=3.6,<3.11
License-File: LICENSE
